endaq/device/__init__.py
endaq/device/base.py
endaq/device/client.py
endaq/device/command_interfaces.py
endaq/device/config.py
endaq/device/configio.py
endaq/device/devinfo.py
endaq/device/endaq.py
endaq/device/exceptions.py
endaq/device/hdlc.py
endaq/device/legacy.py
endaq/device/linux.py
endaq/device/macos.py
endaq/device/measurement.py
endaq/device/response_codes.py
endaq/device/slamstick.py
endaq/device/types.py
endaq/device/util.py
endaq/device/win.py
endaq/device/schemata/__init__.py
endaq/device/schemata/command-response.xml
endaq/device/schemata/flash_package.xml
endaq/device/schemata/mide_config_ui.xml
endaq/device/schemata/mide_manifest.xml
endaq/device/ui_defaults/LOG_0002_025G_DC.py
endaq/device/ui_defaults/LOG_0002_02kG_DC.py
endaq/device/ui_defaults/LOG_0002_100G_DC.py
endaq/device/ui_defaults/LOG_0002_500G_DC.py
endaq/device/ui_defaults/LOG_0003_016G.py
endaq/device/ui_defaults/LOG_0003_200G.py
endaq/device/ui_defaults/LOG_0004_02kG_DC.py
endaq/device/ui_defaults/LOG_0004_500G_DC.py
endaq/device/ui_defaults/S2_D40D200.py
endaq/device/ui_defaults/S2_D8D16.py
endaq/device/ui_defaults/S4_D40.py
endaq/device/ui_defaults/S5_E2000D40.py
endaq/device/ui_defaults/S5_E25D40.py
endaq/device/ui_defaults/Sx_D16.py
endaq/device/ui_defaults/Sx_D40.py
endaq/device/ui_defaults/Sx_D8.py
endaq/device/ui_defaults/Sx_E100D40.py
endaq/device/ui_defaults/Sx_E2000D40.py
endaq/device/ui_defaults/Sx_E25D40.py
endaq/device/ui_defaults/Sx_E500D40.py
endaq/device/ui_defaults/Sx_R100D40.py
endaq/device/ui_defaults/Sx_R2000D40.py
endaq/device/ui_defaults/Sx_R500D40.py
endaq/device/ui_defaults/W8_E100D40.py
endaq/device/ui_defaults/W8_E2000D40.py
endaq/device/ui_defaults/W8_E25D40.py
endaq/device/ui_defaults/Wx_D40.py
endaq/device/ui_defaults/__init__.py
endaq/device/ui_defaults/default.py
endaq_device-1.4.0.dist-info/licenses/LICENSE
endaq_device-1.4.0.dist-info/METADATA
endaq_device-1.4.0.dist-info/WHEEL
endaq_device-1.4.0.dist-info/top_level.txt
endaq_device-1.4.0.dist-info/RECORD
